hcam_finder/__init__.py
hcam_finder/config.py
hcam_finder/finders.py
hcam_finder/finding_chart.py
hcam_finder/hcam_finder.py
hcam_finder/panstarrs.py
hcam_finder/shapes.py
hcam_finder/skyview.py
hcam_finder/ucam_finder.py
hcam_finder/uspec_finder.py
hcam_finder/ztf.py
hcam_finder/data/Lato-Black.ttf
hcam_finder/data/Lato-Regular.ttf
hcam_finder/data/README.rst
hcam_finder/data/config
hcam_finder/data/configspec.ini
hcam_finder/data/guider_hole_arcseconds.txt
hcam_finder-1.3.10.data/scripts/hfinder
hcam_finder-1.3.10.data/scripts/ufinder
hcam_finder-1.3.10.data/scripts/usfinder
hcam_finder-1.3.10.dist-info/AUTHORS.rst
hcam_finder-1.3.10.dist-info/LICENSE
hcam_finder-1.3.10.dist-info/METADATA
hcam_finder-1.3.10.dist-info/WHEEL
hcam_finder-1.3.10.dist-info/top_level.txt
hcam_finder-1.3.10.dist-info/RECORD
