Metadata-Version: 2.2
Name: hcam_finder
Version: 1.3.10
Summary: Observation planning and finding charts for HiPerCAM
Home-page: https://github.com/HiPERCAM/hcam_finder
Download-URL: https://github.com/HiPERCAM/hcam_finder/archive/v1.3.10.tar.gz
Author: Stuart Littlefair
Author-email: s.littlefair@shef.ac.uk
License: MIT license
Keywords: hcam_finder
Classifier: Development Status :: 2 - Pre-Alpha
Classifier: Intended Audience :: Developers
Classifier: License :: OSI Approved :: MIT License
Classifier: Natural Language :: English
Classifier: Programming Language :: Python :: 2
Classifier: Programming Language :: Python :: 2.6
Classifier: Programming Language :: Python :: 2.7
Classifier: Programming Language :: Python :: 3
Classifier: Programming Language :: Python :: 3.3
Classifier: Programming Language :: Python :: 3.4
Classifier: Programming Language :: Python :: 3.5
License-File: LICENSE
License-File: AUTHORS.rst
Requires-Dist: ginga>=4.0
Requires-Dist: astropy
Requires-Dist: six
Requires-Dist: pillow
Requires-Dist: configobj
Requires-Dist: hcam_widgets>=1.2.2
Dynamic: author
Dynamic: author-email
Dynamic: classifier
Dynamic: description
Dynamic: download-url
Dynamic: home-page
Dynamic: keywords
Dynamic: license
Dynamic: requires-dist
Dynamic: summary
